Metadata-Version: 2.4
Name: lebai_sdk
Version: 0.3.5
License-File: LICENSE
Summary: lebai_sdk
Author: rise0chen<rise0chen@163.com>
Author-email: rise0chen<rise0chen@163.com>
Project-URL: Source Code, https://github.com/lebai-robotics/lebai-sdk.rs
